leaf/__init__.py
leaf/__main__.py
leaf/bot.py
leaf_bot-0.0.0.dist-info/LICENSE
leaf_bot-0.0.0.dist-info/METADATA
leaf_bot-0.0.0.dist-info/WHEEL
leaf_bot-0.0.0.dist-info/RECORD
